droplet_planning
