Metadata-Version: 1.0
Name: droplet-planning
Version: 0.2.post1
Summary: Add description here.
Home-page: https://github.com/wheeler-microfluidics/droplet-planning
Author: Anonymous
Author-email: you@mail.com
License: GPL
Platform: UNKNOWN
